kabbes_menu/CONFIG.json
kabbes_menu/CRTI.py
kabbes_menu/Client.py
kabbes_menu/Menu.py
kabbes_menu/__init__.py
kabbes_menu/__main__.py
kabbes_menu-0.2.0.dist-info/LICENSE
kabbes_menu-0.2.0.dist-info/METADATA
kabbes_menu-0.2.0.dist-info/WHEEL
kabbes_menu-0.2.0.dist-info/top_level.txt
kabbes_menu-0.2.0.dist-info/RECORD
